configium/__init__.py
configium/exceptions.py
configium/manager.py
configium/serializers.py
configium/validators.py
configium-0.1.0.dist-info/licenses/LICENSE
configium-0.1.0.dist-info/METADATA
configium-0.1.0.dist-info/WHEEL
configium-0.1.0.dist-info/top_level.txt
configium-0.1.0.dist-info/RECORD
