Metadata-Version: 2.4
Name: configium
Version: 0.1.0
Summary: A smart configuration manager with auto-save and type validation
Author-email: spacelit <spacelit@qq.com>
License: MIT
Project-URL: Homepage, https://github.com/Konecos/configium
Project-URL: Documentation, https://github.com/Konecos/configium#readme
Project-URL: Repository, https://github.com/Konecos/configium
Project-URL: Issues, https://github.com/Konecos/configium/issues
Keywords: config,configuration,settings,yaml,json,toml
Classifier: Development Status :: 4 - Beta
Classifier: Intended Audience :: Developers
Classifier: License :: OSI Approved :: MIT License
Classifier: Programming Language :: Python :: 3
Classifier: Programming Language :: Python :: 3.8
Classifier: Programming Language :: Python :: 3.9
Classifier: Programming Language :: Python :: 3.10
Classifier: Programming Language :: Python :: 3.11
Classifier: Programming Language :: Python :: 3.12
Requires-Python: >=3.8
License-File: LICENSE
Requires-Dist: pydantic>=2.0.0
Requires-Dist: pyyaml>=6.0
Requires-Dist: toml>=0.10.2
Dynamic: license-file
